Metadata-Version: 1.0
Name: cwf
Version: 1.2
Summary: Library that sits between django and a website
Home-page: https://cwf.readthedocs.org
Author: Stephen Moore
Author-email: stephen@delfick.com
License: WTFPL
Keywords: django website
Platform: UNKNOWN
